LICENSE
README.md
setup.py
eyesonly/__init__.py
eyesonly/exceptions.py
eyesonly/secret.py
eyesonly.egg-info/PKG-INFO
eyesonly.egg-info/SOURCES.txt
eyesonly.egg-info/dependency_links.txt
eyesonly.egg-info/requires.txt
eyesonly.egg-info/top_level.txt
eyesonly/acl/__init__.py
eyesonly/acl/acl.py
eyesonly/acl/acl_type.py
eyesonly/acl/providers/__init__.py
eyesonly/acl/providers/base_acl_provider.py
eyesonly/acl/providers/base_file_acl_provider.py
eyesonly/acl/providers/env_acl_provider.py
eyesonly/acl/providers/json_acl_provider.py
eyesonly/acl/providers/toml_acl_provider.py
eyesonly/tests/__init__.py
eyesonly/tests/unit/__init__.py
eyesonly/tests/unit/test_secret.py
eyesonly/tests/unit/acl_tests/__init__.py
eyesonly/tests/unit/acl_tests/provider_tests/__init__.py
eyesonly/tests/unit/acl_tests/provider_tests/test_base_acl_provider.py
eyesonly/tests/unit/acl_tests/provider_tests/test_base_file_acl_provider.py
eyesonly/tests/unit/acl_tests/provider_tests/test_env_acl_provider.py
eyesonly/tests/unit/acl_tests/provider_tests/test_json_acl_provider.py
eyesonly/tests/unit/acl_tests/provider_tests/test_toml_acl_provider.py