Metadata-Version: 2.1
Name: eyesonly
Version: 0.0.2
Summary: A package to avoid having leaks of secrets
Home-page: https://github.com/diegojromerolopez/eyesonly
Author: Diego J. Romero López
Author-email: diegojromerolopez@gmail.com
License: MIT
Keywords: secrets,leaks,isolation
Classifier: Programming Language :: Python :: Implementation :: CPython
Classifier: Programming Language :: Python :: Implementation :: PyPy
Classifier: Programming Language :: Python :: 3.7
Classifier: Programming Language :: Python :: 3.8
Classifier: Programming Language :: Python :: 3.9
Classifier: Programming Language :: Python :: 3.10
Classifier: Programming Language :: Python :: 3.11
Classifier: Topic :: Software Development :: Libraries
Classifier: Development Status :: 3 - Alpha
Classifier: License :: OSI Approved :: MIT License
License-File: LICENSE
